[{"profile_id":173294,"score":55939,"full_name":"William"},{"profile_id":734801,"score":51633,"full_name":"Binbin Qi"},{"profile_id":5349647,"score":49021,"full_name":"goc3"},{"profile_id":1887879,"score":48685,"full_name":"ChrisR"},{"profile_id":17355128,"score":48172,"full_name":"Rafael S.T. Vieira"},{"profile_id":15363629,"score":47566,"full_name":"Christian Schröder"},{"profile_id":615500,"score":46215,"full_name":"Athi"},{"profile_id":12862873,"score":45012,"full_name":"Dyuman Joshi"},{"profile_id":17719399,"score":44975,"full_name":"Lincoln Poon"},{"profile_id":10491973,"score":43380,"full_name":"David Hill"}]